[
  {
    "departamento": "TOTAL",
    "total": 8750000,
    "validos": 51.25,
    "hora": "27/04/2026 18:00 h",
    "candidato_id": "keiko-fujimori",
    "candidato": "Keiko Fujimori",
    "color": "#fd6600",
    "partido": "Fuerza Popular",
    "partido_id": "fuerza-popular",
    "region": "total",
    "conteo": 98.5
  },
  {
    "departamento": "TOTAL",
    "total": 8320000,
    "validos": 48.75,
    "hora": "27/04/2026 18:00 h",
    "candidato_id": "roberto-sanchez",
    "candidato": "Roberto Sánchez",
    "color": "#20a73c",
    "partido": "Juntos por el Perú",
    "partido_id": "juntos-por-el-peru",
    "region": "total",
    "conteo": 98.5
  },
  {
    "departamento": "TOTAL",
    "total": 95000,
    "validos": 0.56,
    "hora": "27/04/2026 18:00 h",
    "candidato_id": "blanco",
    "candidato": "Voto en blanco",
    "color": "#cccccc",
    "partido": "",
    "partido_id": "blanco",
    "region": "total",
    "conteo": 98.5
  },
  {
    "departamento": "TOTAL",
    "total": 78000,
    "validos": 0.46,
    "hora": "27/04/2026 18:00 h",
    "candidato_id": "nulo",
    "candidato": "Voto nulo",
    "color": "#999999",
    "partido": "",
    "partido_id": "nulo",
    "region": "total",
    "conteo": 98.5
  },
  {
    "departamento": "AMAZONAS",
    "total": 167580,
    "validos": 57,
    "hora": "27/04/2026 18:00 h",
    "candidato_id": "keiko-fujimori",
    "candidato": "Keiko Fujimori",
    "color": "#fd6600",
    "partido": "Fuerza Popular",
    "partido_id": "fuerza-popular",
    "region": "amazonas",
    "conteo": 98.2
  },
  {
    "departamento": "AMAZONAS",
    "total": 126420,
    "validos": 43,
    "hora": "27/04/2026 18:00 h",
    "candidato_id": "roberto-sanchez",
    "candidato": "Roberto Sánchez",
    "color": "#20a73c",
    "partido": "Juntos por el Perú",
    "partido_id": "juntos-por-el-peru",
    "region": "amazonas",
    "conteo": 98.2
  },
  {
    "departamento": "ANCASH",
    "total": 220320,
    "validos": 51,
    "hora": "27/04/2026 18:00 h",
    "candidato_id": "keiko-fujimori",
    "candidato": "Keiko Fujimori",
    "color": "#fd6600",
    "partido": "Fuerza Popular",
    "partido_id": "fuerza-popular",
    "region": "ancash",
    "conteo": 96.6
  },
  {
    "departamento": "ANCASH",
    "total": 211680,
    "validos": 49,
    "hora": "27/04/2026 18:00 h",
    "candidato_id": "roberto-sanchez",
    "candidato": "Roberto Sánchez",
    "color": "#20a73c",
    "partido": "Juntos por el Perú",
    "partido_id": "juntos-por-el-peru",
    "region": "ancash",
    "conteo": 96.6
  },
  {
    "departamento": "APURIMAC",
    "total": 188700,
    "validos": 51,
    "hora": "27/04/2026 18:00 h",
    "candidato_id": "keiko-fujimori",
    "candidato": "Keiko Fujimori",
    "color": "#fd6600",
    "partido": "Fuerza Popular",
    "partido_id": "fuerza-popular",
    "region": "apurimac",
    "conteo": 95
  },
  {
    "departamento": "APURIMAC",
    "total": 181300,
    "validos": 49,
    "hora": "27/04/2026 18:00 h",
    "candidato_id": "roberto-sanchez",
    "candidato": "Roberto Sánchez",
    "color": "#20a73c",
    "partido": "Juntos por el Perú",
    "partido_id": "juntos-por-el-peru",
    "region": "apurimac",
    "conteo": 95
  },
  {
    "departamento": "AREQUIPA",
    "total": 143820,
    "validos": 47,
    "hora": "27/04/2026 18:00 h",
    "candidato_id": "keiko-fujimori",
    "candidato": "Keiko Fujimori",
    "color": "#fd6600",
    "partido": "Fuerza Popular",
    "partido_id": "fuerza-popular",
    "region": "arequipa",
    "conteo": 95.8
  },
  {
    "departamento": "AREQUIPA",
    "total": 162180,
    "validos": 53,
    "hora": "27/04/2026 18:00 h",
    "candidato_id": "roberto-sanchez",
    "candidato": "Roberto Sánchez",
    "color": "#20a73c",
    "partido": "Juntos por el Perú",
    "partido_id": "juntos-por-el-peru",
    "region": "arequipa",
    "conteo": 95.8
  },
  {
    "departamento": "AYACUCHO",
    "total": 218310,
    "validos": 57,
    "hora": "27/04/2026 18:00 h",
    "candidato_id": "keiko-fujimori",
    "candidato": "Keiko Fujimori",
    "color": "#fd6600",
    "partido": "Fuerza Popular",
    "partido_id": "fuerza-popular",
    "region": "ayacucho",
    "conteo": 97.4
  },
  {
    "departamento": "AYACUCHO",
    "total": 164690,
    "validos": 43,
    "hora": "27/04/2026 18:00 h",
    "candidato_id": "roberto-sanchez",
    "candidato": "Roberto Sánchez",
    "color": "#20a73c",
    "partido": "Juntos por el Perú",
    "partido_id": "juntos-por-el-peru",
    "region": "ayacucho",
    "conteo": 97.4
  },
  {
    "departamento": "CAJAMARCA",
    "total": 36540,
    "validos": 42,
    "hora": "27/04/2026 18:00 h",
    "candidato_id": "keiko-fujimori",
    "candidato": "Keiko Fujimori",
    "color": "#fd6600",
    "partido": "Fuerza Popular",
    "partido_id": "fuerza-popular",
    "region": "cajamarca",
    "conteo": 96.6
  },
  {
    "departamento": "CAJAMARCA",
    "total": 50460,
    "validos": 58,
    "hora": "27/04/2026 18:00 h",
    "candidato_id": "roberto-sanchez",
    "candidato": "Roberto Sánchez",
    "color": "#20a73c",
    "partido": "Juntos por el Perú",
    "partido_id": "juntos-por-el-peru",
    "region": "cajamarca",
    "conteo": 96.6
  },
  {
    "departamento": "CALLAO",
    "total": 132000,
    "validos": 44,
    "hora": "27/04/2026 18:00 h",
    "candidato_id": "keiko-fujimori",
    "candidato": "Keiko Fujimori",
    "color": "#fd6600",
    "partido": "Fuerza Popular",
    "partido_id": "fuerza-popular",
    "region": "callao",
    "conteo": 95
  },
  {
    "departamento": "CALLAO",
    "total": 168000,
    "validos": 56,
    "hora": "27/04/2026 18:00 h",
    "candidato_id": "roberto-sanchez",
    "candidato": "Roberto Sánchez",
    "color": "#20a73c",
    "partido": "Juntos por el Perú",
    "partido_id": "juntos-por-el-peru",
    "region": "callao",
    "conteo": 95
  },
  {
    "departamento": "CUSCO",
    "total": 168560,
    "validos": 56,
    "hora": "27/04/2026 18:00 h",
    "candidato_id": "keiko-fujimori",
    "candidato": "Keiko Fujimori",
    "color": "#fd6600",
    "partido": "Fuerza Popular",
    "partido_id": "fuerza-popular",
    "region": "cusco",
    "conteo": 95.8
  },
  {
    "departamento": "CUSCO",
    "total": 132440,
    "validos": 44,
    "hora": "27/04/2026 18:00 h",
    "candidato_id": "roberto-sanchez",
    "candidato": "Roberto Sánchez",
    "color": "#20a73c",
    "partido": "Juntos por el Perú",
    "partido_id": "juntos-por-el-peru",
    "region": "cusco",
    "conteo": 95.8
  },
  {
    "departamento": "HUANCAVELICA",
    "total": 184080,
    "validos": 52,
    "hora": "27/04/2026 18:00 h",
    "candidato_id": "keiko-fujimori",
    "candidato": "Keiko Fujimori",
    "color": "#fd6600",
    "partido": "Fuerza Popular",
    "partido_id": "fuerza-popular",
    "region": "huancavelica",
    "conteo": 98.2
  },
  {
    "departamento": "HUANCAVELICA",
    "total": 169920,
    "validos": 48,
    "hora": "27/04/2026 18:00 h",
    "candidato_id": "roberto-sanchez",
    "candidato": "Roberto Sánchez",
    "color": "#20a73c",
    "partido": "Juntos por el Perú",
    "partido_id": "juntos-por-el-peru",
    "region": "huancavelica",
    "conteo": 98.2
  },
  {
    "departamento": "HUANUCO",
    "total": 215730,
    "validos": 51,
    "hora": "27/04/2026 18:00 h",
    "candidato_id": "keiko-fujimori",
    "candidato": "Keiko Fujimori",
    "color": "#fd6600",
    "partido": "Fuerza Popular",
    "partido_id": "fuerza-popular",
    "region": "huanuco",
    "conteo": 97.4
  },
  {
    "departamento": "HUANUCO",
    "total": 207270,
    "validos": 49,
    "hora": "27/04/2026 18:00 h",
    "candidato_id": "roberto-sanchez",
    "candidato": "Roberto Sánchez",
    "color": "#20a73c",
    "partido": "Juntos por el Perú",
    "partido_id": "juntos-por-el-peru",
    "region": "huanuco",
    "conteo": 97.4
  },
  {
    "departamento": "ICA",
    "total": 84560,
    "validos": 56,
    "hora": "27/04/2026 18:00 h",
    "candidato_id": "keiko-fujimori",
    "candidato": "Keiko Fujimori",
    "color": "#fd6600",
    "partido": "Fuerza Popular",
    "partido_id": "fuerza-popular",
    "region": "ica",
    "conteo": 95.8
  },
  {
    "departamento": "ICA",
    "total": 66440,
    "validos": 44,
    "hora": "27/04/2026 18:00 h",
    "candidato_id": "roberto-sanchez",
    "candidato": "Roberto Sánchez",
    "color": "#20a73c",
    "partido": "Juntos por el Perú",
    "partido_id": "juntos-por-el-peru",
    "region": "ica",
    "conteo": 95.8
  },
  {
    "departamento": "JUNIN",
    "total": 160720,
    "validos": 49,
    "hora": "27/04/2026 18:00 h",
    "candidato_id": "keiko-fujimori",
    "candidato": "Keiko Fujimori",
    "color": "#fd6600",
    "partido": "Fuerza Popular",
    "partido_id": "fuerza-popular",
    "region": "junin",
    "conteo": 97.4
  },
  {
    "departamento": "JUNIN",
    "total": 167280,
    "validos": 51,
    "hora": "27/04/2026 18:00 h",
    "candidato_id": "roberto-sanchez",
    "candidato": "Roberto Sánchez",
    "color": "#20a73c",
    "partido": "Juntos por el Perú",
    "partido_id": "juntos-por-el-peru",
    "region": "junin",
    "conteo": 97.4
  },
  {
    "departamento": "LA LIBERTAD",
    "total": 137460,
    "validos": 58,
    "hora": "27/04/2026 18:00 h",
    "candidato_id": "keiko-fujimori",
    "candidato": "Keiko Fujimori",
    "color": "#fd6600",
    "partido": "Fuerza Popular",
    "partido_id": "fuerza-popular",
    "region": "la-libertad",
    "conteo": 96.6
  },
  {
    "departamento": "LA LIBERTAD",
    "total": 99540,
    "validos": 42,
    "hora": "27/04/2026 18:00 h",
    "candidato_id": "roberto-sanchez",
    "candidato": "Roberto Sánchez",
    "color": "#20a73c",
    "partido": "Juntos por el Perú",
    "partido_id": "juntos-por-el-peru",
    "region": "la-libertad",
    "conteo": 96.6
  },
  {
    "departamento": "LAMBAYEQUE",
    "total": 72680,
    "validos": 46,
    "hora": "27/04/2026 18:00 h",
    "candidato_id": "keiko-fujimori",
    "candidato": "Keiko Fujimori",
    "color": "#fd6600",
    "partido": "Fuerza Popular",
    "partido_id": "fuerza-popular",
    "region": "lambayeque",
    "conteo": 97.4
  },
  {
    "departamento": "LAMBAYEQUE",
    "total": 85320,
    "validos": 54,
    "hora": "27/04/2026 18:00 h",
    "candidato_id": "roberto-sanchez",
    "candidato": "Roberto Sánchez",
    "color": "#20a73c",
    "partido": "Juntos por el Perú",
    "partido_id": "juntos-por-el-peru",
    "region": "lambayeque",
    "conteo": 97.4
  },
  {
    "departamento": "LIMA",
    "total": 147390,
    "validos": 51,
    "hora": "27/04/2026 18:00 h",
    "candidato_id": "keiko-fujimori",
    "candidato": "Keiko Fujimori",
    "color": "#fd6600",
    "partido": "Fuerza Popular",
    "partido_id": "fuerza-popular",
    "region": "lima",
    "conteo": 98.2
  },
  {
    "departamento": "LIMA",
    "total": 141610,
    "validos": 49,
    "hora": "27/04/2026 18:00 h",
    "candidato_id": "roberto-sanchez",
    "candidato": "Roberto Sánchez",
    "color": "#20a73c",
    "partido": "Juntos por el Perú",
    "partido_id": "juntos-por-el-peru",
    "region": "lima",
    "conteo": 98.2
  },
  {
    "departamento": "LIMA-PROVINCIAS",
    "total": 54600,
    "validos": 42,
    "hora": "27/04/2026 18:00 h",
    "candidato_id": "keiko-fujimori",
    "candidato": "Keiko Fujimori",
    "color": "#fd6600",
    "partido": "Fuerza Popular",
    "partido_id": "fuerza-popular",
    "region": "lima-provincias",
    "conteo": 95
  },
  {
    "departamento": "LIMA-PROVINCIAS",
    "total": 75400,
    "validos": 58,
    "hora": "27/04/2026 18:00 h",
    "candidato_id": "roberto-sanchez",
    "candidato": "Roberto Sánchez",
    "color": "#20a73c",
    "partido": "Juntos por el Perú",
    "partido_id": "juntos-por-el-peru",
    "region": "lima-provincias",
    "conteo": 95
  },
  {
    "departamento": "LORETO",
    "total": 83720,
    "validos": 52,
    "hora": "27/04/2026 18:00 h",
    "candidato_id": "keiko-fujimori",
    "candidato": "Keiko Fujimori",
    "color": "#fd6600",
    "partido": "Fuerza Popular",
    "partido_id": "fuerza-popular",
    "region": "loreto",
    "conteo": 95.8
  },
  {
    "departamento": "LORETO",
    "total": 77280,
    "validos": 48,
    "hora": "27/04/2026 18:00 h",
    "candidato_id": "roberto-sanchez",
    "candidato": "Roberto Sánchez",
    "color": "#20a73c",
    "partido": "Juntos por el Perú",
    "partido_id": "juntos-por-el-peru",
    "region": "loreto",
    "conteo": 95.8
  },
  {
    "departamento": "MADRE DE DIOS",
    "total": 66720,
    "validos": 48,
    "hora": "27/04/2026 18:00 h",
    "candidato_id": "keiko-fujimori",
    "candidato": "Keiko Fujimori",
    "color": "#fd6600",
    "partido": "Fuerza Popular",
    "partido_id": "fuerza-popular",
    "region": "madre-de-dios",
    "conteo": 98.2
  },
  {
    "departamento": "MADRE DE DIOS",
    "total": 72280,
    "validos": 52,
    "hora": "27/04/2026 18:00 h",
    "candidato_id": "roberto-sanchez",
    "candidato": "Roberto Sánchez",
    "color": "#20a73c",
    "partido": "Juntos por el Perú",
    "partido_id": "juntos-por-el-peru",
    "region": "madre-de-dios",
    "conteo": 98.2
  },
  {
    "departamento": "MOQUEGUA",
    "total": 182280,
    "validos": 49,
    "hora": "27/04/2026 18:00 h",
    "candidato_id": "keiko-fujimori",
    "candidato": "Keiko Fujimori",
    "color": "#fd6600",
    "partido": "Fuerza Popular",
    "partido_id": "fuerza-popular",
    "region": "moquegua",
    "conteo": 96.6
  },
  {
    "departamento": "MOQUEGUA",
    "total": 189720,
    "validos": 51,
    "hora": "27/04/2026 18:00 h",
    "candidato_id": "roberto-sanchez",
    "candidato": "Roberto Sánchez",
    "color": "#20a73c",
    "partido": "Juntos por el Perú",
    "partido_id": "juntos-por-el-peru",
    "region": "moquegua",
    "conteo": 96.6
  },
  {
    "departamento": "PASCO",
    "total": 129540,
    "validos": 51,
    "hora": "27/04/2026 18:00 h",
    "candidato_id": "keiko-fujimori",
    "candidato": "Keiko Fujimori",
    "color": "#fd6600",
    "partido": "Fuerza Popular",
    "partido_id": "fuerza-popular",
    "region": "pasco",
    "conteo": 98.2
  },
  {
    "departamento": "PASCO",
    "total": 124460,
    "validos": 49,
    "hora": "27/04/2026 18:00 h",
    "candidato_id": "roberto-sanchez",
    "candidato": "Roberto Sánchez",
    "color": "#20a73c",
    "partido": "Juntos por el Perú",
    "partido_id": "juntos-por-el-peru",
    "region": "pasco",
    "conteo": 98.2
  },
  {
    "departamento": "PIURA",
    "total": 75950,
    "validos": 49,
    "hora": "27/04/2026 18:00 h",
    "candidato_id": "keiko-fujimori",
    "candidato": "Keiko Fujimori",
    "color": "#fd6600",
    "partido": "Fuerza Popular",
    "partido_id": "fuerza-popular",
    "region": "piura",
    "conteo": 95
  },
  {
    "departamento": "PIURA",
    "total": 79050,
    "validos": 51,
    "hora": "27/04/2026 18:00 h",
    "candidato_id": "roberto-sanchez",
    "candidato": "Roberto Sánchez",
    "color": "#20a73c",
    "partido": "Juntos por el Perú",
    "partido_id": "juntos-por-el-peru",
    "region": "piura",
    "conteo": 95
  },
  {
    "departamento": "PUNO",
    "total": 103500,
    "validos": 45,
    "hora": "27/04/2026 18:00 h",
    "candidato_id": "keiko-fujimori",
    "candidato": "Keiko Fujimori",
    "color": "#fd6600",
    "partido": "Fuerza Popular",
    "partido_id": "fuerza-popular",
    "region": "puno",
    "conteo": 95
  },
  {
    "departamento": "PUNO",
    "total": 126500,
    "validos": 55,
    "hora": "27/04/2026 18:00 h",
    "candidato_id": "roberto-sanchez",
    "candidato": "Roberto Sánchez",
    "color": "#20a73c",
    "partido": "Juntos por el Perú",
    "partido_id": "juntos-por-el-peru",
    "region": "puno",
    "conteo": 95
  },
  {
    "departamento": "SAN MARTIN",
    "total": 106720,
    "validos": 46,
    "hora": "27/04/2026 18:00 h",
    "candidato_id": "keiko-fujimori",
    "candidato": "Keiko Fujimori",
    "color": "#fd6600",
    "partido": "Fuerza Popular",
    "partido_id": "fuerza-popular",
    "region": "san-martin",
    "conteo": 96.6
  },
  {
    "departamento": "SAN MARTIN",
    "total": 125280,
    "validos": 54,
    "hora": "27/04/2026 18:00 h",
    "candidato_id": "roberto-sanchez",
    "candidato": "Roberto Sánchez",
    "color": "#20a73c",
    "partido": "Juntos por el Perú",
    "partido_id": "juntos-por-el-peru",
    "region": "san-martin",
    "conteo": 96.6
  },
  {
    "departamento": "TACNA",
    "total": 42720,
    "validos": 48,
    "hora": "27/04/2026 18:00 h",
    "candidato_id": "keiko-fujimori",
    "candidato": "Keiko Fujimori",
    "color": "#fd6600",
    "partido": "Fuerza Popular",
    "partido_id": "fuerza-popular",
    "region": "tacna",
    "conteo": 98.2
  },
  {
    "departamento": "TACNA",
    "total": 46280,
    "validos": 52,
    "hora": "27/04/2026 18:00 h",
    "candidato_id": "roberto-sanchez",
    "candidato": "Roberto Sánchez",
    "color": "#20a73c",
    "partido": "Juntos por el Perú",
    "partido_id": "juntos-por-el-peru",
    "region": "tacna",
    "conteo": 98.2
  },
  {
    "departamento": "TUMBES",
    "total": 84280,
    "validos": 43,
    "hora": "27/04/2026 18:00 h",
    "candidato_id": "keiko-fujimori",
    "candidato": "Keiko Fujimori",
    "color": "#fd6600",
    "partido": "Fuerza Popular",
    "partido_id": "fuerza-popular",
    "region": "tumbes",
    "conteo": 95.8
  },
  {
    "departamento": "TUMBES",
    "total": 111720,
    "validos": 57,
    "hora": "27/04/2026 18:00 h",
    "candidato_id": "roberto-sanchez",
    "candidato": "Roberto Sánchez",
    "color": "#20a73c",
    "partido": "Juntos por el Perú",
    "partido_id": "juntos-por-el-peru",
    "region": "tumbes",
    "conteo": 95.8
  },
  {
    "departamento": "UCAYALI",
    "total": 54000,
    "validos": 45,
    "hora": "27/04/2026 18:00 h",
    "candidato_id": "keiko-fujimori",
    "candidato": "Keiko Fujimori",
    "color": "#fd6600",
    "partido": "Fuerza Popular",
    "partido_id": "fuerza-popular",
    "region": "ucayali",
    "conteo": 95
  },
  {
    "departamento": "UCAYALI",
    "total": 66000,
    "validos": 55,
    "hora": "27/04/2026 18:00 h",
    "candidato_id": "roberto-sanchez",
    "candidato": "Roberto Sánchez",
    "color": "#20a73c",
    "partido": "Juntos por el Perú",
    "partido_id": "juntos-por-el-peru",
    "region": "ucayali",
    "conteo": 95
  },
  {
    "departamento": "EXTRANJERO",
    "total": 105560,
    "validos": 58,
    "hora": "27/04/2026 18:00 h",
    "candidato_id": "keiko-fujimori",
    "candidato": "Keiko Fujimori",
    "color": "#fd6600",
    "partido": "Fuerza Popular",
    "partido_id": "fuerza-popular",
    "region": "extranjero",
    "conteo": 88
  },
  {
    "departamento": "EXTRANJERO",
    "total": 76440,
    "validos": 42,
    "hora": "27/04/2026 18:00 h",
    "candidato_id": "roberto-sanchez",
    "candidato": "Roberto Sánchez",
    "color": "#20a73c",
    "partido": "Juntos por el Perú",
    "partido_id": "juntos-por-el-peru",
    "region": "extranjero",
    "conteo": 88
  }
]
